{"name":"Candidate Pool","children":[{"name":"masters","size":36,"children":[{"name":"5+","size":"23","children":[{"id":185232,"userID":188445,"hired":0,"answer":"More than 5 years of experience.","ed_level":"masters","name":"Instructional Designer","exp_level":"5+","tags":["hypertext","hypertext markup language","hyper text markup language","adm","administrative tasks","ado","c","me","adobe","design","graphic design","wordpress","web technolog","web te","web","web development","web technologies","os","x","java","programming","applications","ar","markup language","script","php programming language","purchasing","inventory","equity","base","inventor","ca","canvas","cascading style sheets","sheets","cat","microsoft powerpoint","microsoft w","cms","mcp (os -lg unisys sys)","security","video","css","t","networking","database","mysql database","linux","ms","drupal","e","ec","edi","ent","ess","sql","troubleshooting","hp","integrate","ja","javascript","unisys","lms","mi","micro","micros","microsof","windows","microsoft","microsoft windows","mysql","oc","oo","p","php","php programmin","q","r","sec","sq","ss","st","wi"]},{"id":185232,"userID":188440,"hired":0,"answer":"More than 5 years of experience.","ed_level":"masters","name":"Instructional Designer","exp_level":"5+","tags":["customer relationship management","management","c","me","financial","services","financial services","os","retail","real estate","t","deposits","e","ent","training","retail sales","sales training","sales","its","osi","p","pos","r","referrals","relat","st","us"]},{"id":185232,"userID":188502,"hired":0,"answer":"More than 5 years of experience.","ed_level":"masters","name":"Instructional Designer","exp_level":"5+","tags":["manager","project management","management","project manager","negotiation","negotiation skills","c","me","pricing","personal computer","ar","base","core based trees","ca","electronics","ct","t","ms","e","ec","edi","ent","multimedia","training","go","pc","technical writing","lms","multi","nic","p","r","referrals","sed","series","ul"]},{"id":185232,"userID":188510,"hired":0,"answer":"More than 5 years of experience.","ed_level":"masters","name":"Instructional Designer","exp_level":"5+","tags":["microsoft access","program management","management consulting","project management","customer relationship management","management","presentation skills","software","ach","microsoft office","ado","c","sharepoint","me","sharepoint technologies","adobe","adobe photoshop","adobe indesign","advertising","design","agile","financial","event management","services","web technolog","web te","financial services","web","web technologies","development initiatives","os","x","ar","equity","business objects","ca","consulting","microsoft word","microsoft powerpoint","microsoft w","microsoft excel","coaching","video","connectivity","ct","t","lotus notes","e","ec","ent","ess","training","git","peoplesoft","ile","sales","technical writing","lotus","mi","micro","micros","microsof","microsoft","nec","nic","p","q","r","relat","retention","salesforce","snagit","ss","st","ul","us"]},{"id":185232,"userID":188507,"hired":0,"answer":"More than 5 years of experience.","ed_level":"masters","name":"Instructional Designer","exp_level":"5+","tags":["project management","product management","management","software","tableau software","hypertext","hypertext markup language","c","me","engineering","business requirements","business development","os","x","java","programming","oracle","ar","markup language","java programming language","script","shell script","scripting language","php programming language","quality assurance","quality","quality center","insurance","base","shell scripting","structured query language","proc","consulting","microsoft excel","tableau","ct","t","database","mysql database","ms","e","ec","ent","java prog","ess","query","sql","hbase","hive","hp","ibm","process improvement","ja","javascript","mi","micro","micros","microsof","microsoft","mysql","oc","p","php","php programmin","q","qual","structured query","r","scriptin","sq","ss","st","struct","ul","us"]},{"id":185232,"userID":188508,"hired":0,"answer":"More than 5 years of experience.","ed_level":"masters","name":"Instructional Designer","exp_level":"5+","tags":["microsoft office","c","pricing","advertising","research","os","ar","real estate","ca","t","e","filing","mi","micro","micros","microsof","microsoft","p","r","st"]},{"id":185232,"userID":188505,"hired":0,"answer":"More than 5 years of experience.","ed_level":"masters","name":"Instructional Designer","exp_level":"5+","tags":["systems administrator","adm","c","me","desk top support","desktop computer","support","technical support","ca","information technology","technology","t","networking","ms","e","ec","edi","multimedia","system","voice","low voltage","mi","multi","nic","orm","p","r","st","syst","syste","ul"]},{"id":185232,"userID":188503,"hired":0,"answer":"More than 5 years of experience.","ed_level":"masters","name":"Instructional Designer","exp_level":"5+","tags":["microsoft access","management","microsoft office","hypertext","french language","hypertext markup language","ado","c","me","adobe","design","desktop computer","systems development","os","x","product design","applications","desktop applications","ar","markup language","extensible markup language (xml)","english language","planning","strategic planning","ca","canvas","cat","ct","t","strategic initiatives","ms","e","ec","edi","ent","ess","training","gl","system","project leader","leadership","project leadership","lms","mi","micro","micros","microsof","microsoft","ml","oc","p","r","ss","st","syst","syste"]},{"id":185232,"userID":188460,"hired":0,"answer":"More than 5 years of experience.","ed_level":"masters","name":"Instructional Designer","exp_level":"5+","tags":["management consulting","project management","management","asset management","macromedia dreamweaver","microsoft office","ado","c","me","adobe","adobe illustrator","adobe photoshop","adobe acrobat","adobe indesign","design","graphic design","personal computer","desktop computer","os","mac","x","apple","apple macintosh","ar","word processing","white papers","real estate","proc","consulting","sheets","microsoft word","microsoft powerpoint","microsoft w","microsoft publisher","microsoft vis","desktop publishing","security","video","ct","t","publishing","ms","e","ec","edi","ent","ess","macromedia flash","macromedia","pc","ms project","litigation","mi","micro","micros","microsof","microsoft","microsoft visio","visio","microsoft project","oc","p","q","quarkxpress","r","sec","ss","st","ul","us"]},{"id":185232,"userID":188506,"hired":0,"answer":"More than 5 years of experience.","ed_level":"masters","name":"Instructional Designer","exp_level":"5+","tags":["management","software","macromedia dreamweaver","microsoft office","development activities","python","hypertext","python programming","hypertext markup language","python programming language","owl programming language","ado","c","me","adobe","adobe photoshop","design","graphic design","agile","engineering","web technolog","web te","web","web technologies","research","os","mac","x","human resources","apple","apple macintosh","apple macintosh operating system","programming","support","ar","markup language","local area network","wide area network","blue prints","blueprints","team player","pathway","scheduling","ca","canvas","denebra canvas","cascading style sheets","sheets","microsoft w","microsoft excel","cisco","cloud computing","hardware","security","information security","css","ct","t","networking","ms","e","ec","edi","ent","training","filing","macromedia","hr","hardware/systems","https","system","ile","lms","medical","mi","micro","micros","microsof","windows","microsoft","microsoft windows","oc","orm","p","r","schematics","sec","ss","st","syst","syste","tea","ul","wi"]},{"id":185232,"userID":188464,"hired":0,"answer":"More than 5 years of experience.","ed_level":"masters","name":"Instructional Designer","exp_level":"5+","tags":["macromedia dreamweaver","c","me","mac","english language","e","edi","macromedia","gl","r"]},{"id":185232,"userID":188491,"hired":0,"answer":"More than 5 years of experience.","ed_level":"masters","name":"Instructional Designer","exp_level":"5+","tags":["project management","customer relationship management","change management","microsoft change management","management","c","me","leadership development","os","human resources","assessments","sap","scheduling","ct","t","ms","e","ec","ent","ess","training","hr","leadership","lms","logistics","mi","micro","micros","microsof","microsoft","netweaver","p","r","relat","roi","ss","st","ul","us"]},{"id":185232,"userID":188497,"hired":0,"answer":"More than 5 years of experience.","ed_level":"masters","name":"Instructional Designer","exp_level":"5+","tags":["microsoft access","project management","risk ma","management","risk management","software","customer service","microsoft office","microsoft outlook","ado","c","sharepoint","me","sharepoint technologies","adobe","adobe photoshop","adobe acrobat","desktop computer","services","web technolog","web te","web","web technologies","telephony","os","x","human resources","support","applications","ar","computer telephony integration (cti)","insurance","call center","ca","cat","microsoft word","microsoft powerpoint","microsoft w","microsoft excel","microsoft vis","information technology","technology","ct","t","ms","light emitting diode","e","ec","ent","ess","training","hr","git","sales","integrate","ja","lms","logistics","mi","micro","micros","microsof","microsoft","microsoft visio","visio","oo","orm","p","r","snagit","ss","st","ul","us"]},{"id":185232,"userID":188498,"hired":0,"answer":"More than 5 years of experience.","ed_level":"masters","name":"Instructional Designer","exp_level":"5+","tags":["microsoft outlook","c","research","os","x","ar","microsoft internet explorer","microsoft word","microsoft powerpoint","microsoft w","microsoft excel","t","e","ent","internet","matlab","mi","micro","micros","microsof","microsoft","oo","p","r","st","statistics","xpl"]},{"id":185232,"userID":188477,"hired":0,"answer":"More than 5 years of experience.","ed_level":"masters","name":"Instructional Designer","exp_level":"5+","tags":["project management","management","c","me","support","technical support","english language","assessments","quality assurance","quality","ca","consulting","ct","t","networking","publishing","e","ec","ent","ess","gl","integrate","test","nic","p","q","qual","r","ss","st","ul"]},{"id":185232,"userID":188454,"hired":1,"answer":"More than 5 years of experience.","ed_level":"masters","name":"Instructional Designer","exp_level":"5+","tags":["customer relationship management","marketing management","management","hypertext","hypertext markup language","ado","c","me","adobe","business development","os","x","ar","markup language","quality assurance","quality","quality control","scheduling","ca","patient care","use cases","cat","microsoft word","microsoft powerpoint","microsoft w","microsoft excel","cms","information technology","technology","video","t","ms","e","ec","edi","ent","ess","training","lms","medical","mi","micro","micros","microsof","microsoft","oc","orm","p","publications","q","qual","r","relat","ss","st","ul","us"]},{"id":185232,"userID":188466,"hired":0,"answer":"More than 5 years of experience.","ed_level":"masters","name":"Instructional Designer","exp_level":"5+","tags":["content management","project management","management","spss (math/stats pkg)","software","microsoft office","hypertext","french language","hypertext markup language","ado","c","me","adobe","adobe photoshop","adobe premiere","advertising","wordpress","financial","web technolog","web te","analytics","web","google analytics","web technologies","os","x","java","google apps","programming","ar","markup language","java programming language","english language","coding","planning","strategic planning","ca","cascading style sheets","sheets","microsoft w","css","ct","t","e","ec","edi","ent","java prog","ess","query","gl","go","ibm","ja","jquery","logistics","mi","micro","micros","microsof","windows","microsoft","microsoft windows","oc","oo","p","q","r","sp","sps","ss","st","wi"]},{"id":185232,"userID":188478,"hired":0,"answer":"More than 5 years of experience.","ed_level":"masters","name":"Instructional Designer","exp_level":"5+","tags":["manager","project management","customer relationship management","software configuration management","marketing management","management","configuration management","project manager","software","acquisitions","mergers","macromedia dreamweaver","microsoft office","hypertext","hypertext markup language","order entry","communication skills","ado","c","sharepoint","me","sharepoint technologies","adobe","adobe illustrator","adobe photoshop","adobe acrobat","help desk support","financial","personal computer","amazon elastic mapreduce","services","financial services","system analyst","business requirements","verbal communication skills","os","mac","x","apple","apple macintosh","architect","architecture","support","ar","markup language","xa (extended architecture)","arm","script","bal","health care industry","data general eclipse","quick books","planning","project planning","ca","proc","consulting","sheets","cash flow","cat","microsoft publisher","microsoft vis","information technology","technology","communication","verbal communication","security","data general","corel","corel wordperfect","wordperfect","ct","t","eclipse","help desk","ms","lotus notes","ds","e","ec","edi","emr","ent","multimedia","ess","training","macromedia flash","macromedia","hr","troubleshooting","pc","ibm","system","process improvement","ms project","lms","lotus","mckesson","mi","micro","micros","microsof","microsoft","microsoft visio","visio","microsoft project","multi","nic","nursing","oc","oo","sun","orm","p","q","quickbooks","r","rad","relat","remedy","rf","scm","sec","vital signs","ss","sso","st","syst","syste","ul","us"]},{"id":185232,"userID":188470,"hired":0,"answer":"More than 5 years of experience.","ed_level":"masters","name":"Instructional Designer","exp_level":"5+","tags":["account manager","manager","project management","management","hypertext","hypertext markup language","ado","c","me","adobe","leadership development","mac","x","java","human resources","ar","markup language","script","insurance","automation","ct","t","ms","e","ec","edi","ent","training","macromedia flash","macromedia","ja","javascript","leadership","lms","p","r","series"]},{"id":185232,"userID":188515,"hired":0,"answer":"More than 5 years of experience.","ed_level":"masters","name":"Instructional Designer","exp_level":"5+","tags":["management","hypertext","hypertext markup language","ado","dos","c","me","adobe","adobe photoshop","ambulatory services","services","os","mac","x","java","ar","markup language","extensible markup language (xml)","script","scheduling","ca","t","help desk","ms","e","ec","edi","ent","training","macromedia flash","macromedia","https","voice recognition","voice","ix","ja","javascript","lms","ml","nix","oo","p","r","ul","us"]},{"id":185232,"userID":188468,"hired":0,"answer":"More than 5 years of experience.","ed_level":"masters","name":"Instructional Designer","exp_level":"5+","tags":["user documentation","manager","project management","document management","marketing management","management","project manager","software","software development","microsoft office","hypertext","hypertext markup language","ado","c","sharepoint","me","sharepoint technologies","adobe","adobe photoshop","adobe acrobat","payroll","design","graphic design","investment management","web technolog","web te","web","web technologies","os","mac","x","infrastructure","geographic information system","design documents","ar","markup language","arm","budgeting","quality assurance","quality","audit","pharmaceutical industry","documentum (wkflow sw)","sap","ca","proc","cat","microsoft word","microsoft powerpoint","microsoft w","microsoft excel","microsoft vis","communications","information technology","technology","communication","security","ct","t","diagnostics","technical documentation","documentum","drafting","e","ec","edi","ent","evaluate","training","facilitator","git","system","internet","intranet","test","technical writing","mi","micro","micros","microsof","windows","microsoft","microsoft visio","visio","microsoft windows","motorola","nic","oc","orm","p","pdf","q","qual","r","ras","relat","sec","series","snagit","ss","st","struct","syst","syste","us","wi"]},{"id":185232,"userID":188474,"hired":0,"answer":"More than 5 years of experience.","ed_level":"masters","name":"Instructional Designer","exp_level":"5+","tags":["content management","project management","management","software","microsoft office","hypertext","hypertext markup language","ado","c","me","adobe","web technolog","web te","web","web technologies","os","x","ar","markup language","english language","assessments","sas","sheets","video","ct","t","ms","disaster recovery","e","ec","ent","ess","evaluate","training","gl","lms","mba","mi","micro","micros","microsof","microsoft","p","r","ss","st"]},{"id":185232,"userID":184979,"hired":0,"answer":"More than 5 years of experience.","ed_level":"masters","name":"Instructional Designer","exp_level":"5+","tags":["management","statistical analysis","python","python programming","python programming language","c programming language","c++ programming language","c","me","financial","engineering","data analysis","research","os","mac","programming","applications","ar","asic","equity","base","sas","visual basic","microsoft visual basic","data dictionary","c++","forecast","structured query language","ca","proc","cat","microsoft vis","macro (predefined code)","financial statements","ct","t","predict (data dictionary)","predict","database","mysql database","e","ec","edi","ent","query","sql","pc","ibm","test","matlab","mi","micro","micros","microsof","microsoft","microsoft visual","microsoft visual ba","mysql","oc","p","q","structured query","r","sas/stat","sec","securities","sq","st","struct"]}]},{"name":"1-2","size":"0","children":[""]},{"name":"3-5","size":"10","children":[{"id":185232,"userID":188483,"hired":0,"answer":"3-5 years of experience.","ed_level":"masters","name":"Instructional Designer","exp_level":"3-5","tags":["management","asset management","microsoft office","ado","c","me","adobe","financial","os","english language","insurance","investment ba","equity","investment banking","banking industry","manufacturing","bloomberg","business contingency planning","planning","structured query language","financial statements","ct","t","due diligence","e","ec","ent","ess","query","financials","hedge fund","gl","mi","micro","micros","microsof","microsoft","oo","p","q","structured query","r","sec","securities","ss","st","struct","us"]},{"id":185232,"userID":188490,"hired":0,"answer":"3-5 years of experience.","ed_level":"masters","name":"Instructional Designer","exp_level":"3-5","tags":["management","spss (math/stats pkg)","microsoft office","c","me","financial","business analysis","research","os","human resources","infrastructure","ar","financial industry","broadband","planning","strategic planning","credit card","ca","consulting","cat","communications","communication","ct","t","publishing","e","ec","edi","ent","ess","mi","micro","micros","microsof","microsoft","nic","p","r","ras","sp","sps","ss","st","statistics","struct","ul","us"]},{"id":185232,"userID":171749,"hired":0,"answer":"3-5 years of experience.","ed_level":"masters","name":"Instructional Designer","exp_level":"3-5","tags":["acceptance testing","testing","unit testing","management","software","tableau software","generate reports","sql server","microsoft sql server","microsoft office","python","hypertext","python programming","hypertext markup language","python programming language","oracle database","c","me","design","os","x","object oriented design","programming","oracle","ar","markup language","asic","script","scripting language","assessments","mainframe computer","banking industry","base","base sas","sas","visual basic","structured query language","er diagrams","microsoft vis","tableau","citrix","information technology","technology","object orien","security","data modeler","ct","t","database","mysql database","ms","sdlc","unix","e","ec","ent","ess","query","sql","system","ix","test","mi","micro","micros","microsof","microsoft","microsoft visio","visio","microsoft project","sql s","mysql","mysql workbench","workbench","nix","oo","orm","p","pos","q","structured query","r","scriptin","sec","sq","ss","st","statistics","struct","syst","syste","triggers","us","vmware"]},{"id":185232,"userID":188482,"hired":0,"answer":"3-5 years of experience.","ed_level":"masters","name":"Instructional Designer","exp_level":"3-5","tags":["manager","enterprise manager","ach","python","python programming","python programming language","c programming language","c++ programming language","ado","c","me","business analysis","data analysis","business analyst","analytics","google analytics","research","business development","os","x","apache hadoop","java","programming","ar","java programming language","modeling experience","english language","quality assurance","quality","sas","data dictionary","c++","structured query language","market research","ct","t","predict (data dictionary)","predict","e","edi","ent","java prog","ess","query","gl","go","ja","test","mi","micro","micros","microsof","microsoft","oo","p","q","qual","structured query","r","ss","st","struct","us"]},{"id":185232,"userID":188509,"hired":0,"answer":"3-5 years of experience.","ed_level":"masters","name":"Instructional Designer","exp_level":"3-5","tags":["user interface","marketing management","management","analytical skills","microsoft outlook","android","hypertext","hypertext markup language","c programming language","communication skills","ado","c","me","adobe","adobe photoshop","advertising","layout","design","graphic design","ux design","interface design","verbal communication skills","research","os","mac","x","visual design","programming","ar","markup language","business intelligence","english language","bal","best practices","planning","strategic planning","scheduling","ca","consulting","cascading style sheets","sheets","cat","microsoft word","microsoft w","communication","verbal communication","css","ct","t","e","edi","email","ent","ess","evaluate","training","macromedia flash","macromedia","gl","intel","test","mi","micro","micros","microsof","microsoft","nic","oc","oo","p","r","rf","roi","ss","st","ul","us"]},{"id":185232,"userID":188448,"hired":0,"answer":"3-5 years of experience.","ed_level":"masters","name":"Instructional Designer","exp_level":"3-5","tags":["project management","change management","microsoft change management","marketing management","management","spss (math/stats pkg)","talent acquisition","microsoft office","ado","c","me","adobe","adobe photoshop","web technolog","web te","web","web development","web technologies","research","os","api","human resources","human resources information system","ar","data processing","sap","ca","proc","ct","t","e","ec","edi","ent","ess","evaluate","training","git","system","mi","micro","micros","microsof","microsoft","oc","orm","p","q","r","recruiter","snagit","sp","sps","ss","st","syst","syste","wi"]},{"id":185232,"userID":188513,"hired":0,"answer":"3-5 years of experience.","ed_level":"masters","name":"Instructional Designer","exp_level":"3-5","tags":["product management","management","spss (math/stats pkg)","microsoft office","hypertext","hypertext markup language","data entry","adm","administrative assistant","ado","c","me","adobe","adobe illustrator","adobe photoshop","adobe acrobat","pricing","data analysis","research","os","mac","x","ar","markup language","retail","ca","cascading style sheets","sheets","test cases","cat","microsoft word","microsoft w","microsoft excel","communication","written communication","video","css","ct","t","e","ec","edi","ent","macromedia flash","macromedia","test","mi","micro","micros","microsof","microsoft","nic","oo","p","r","recruiting","sp","sps","ss","ssis","st","us"]},{"id":185232,"userID":178464,"hired":0,"answer":"3-5 years of experience.","ed_level":"masters","name":"Instructional Designer","exp_level":"3-5","tags":["software","tableau software","ad hoc reports","python","python programming","python programming language","data mining","c","business analysis","business analyst","analytics","google analytics","os","x","programming","applications","ar","modeling experience","asic","automation","inventory","retail","sas","visual basic","microsoft visual basic","structured query language","inventor","ca","cat","microsoft excel","microsoft vis","tableau","clustering","clusters","ct","t","e","email","ent","mining","ess","query","gl","go","lda","mi","micro","micros","microsof","microsoft","microsoft visual","microsoft visual ba","oc","oo","p","q","structured query","r","ss","st","struct","us"]},{"id":185232,"userID":184380,"hired":0,"answer":"3-5 years of experience.","ed_level":"masters","name":"Instructional Designer","exp_level":"3-5","tags":["management","software","tableau software","microsoft office","data entry","c","me","desktop computer","data analysis","business requirements","analytics","google analytics","os","x","ar","audit","autodesk autocad","autocad d","autodesk","inventory","structured query language","inventor","ca","proc","microsoft word","microsoft powerpoint","microsoft w","microsoft excel","microsoft vis","tableau","collection","collection procedures","security","ct","t","e","ec","ent","ess","query","gl","go","sales","mcad","mcad solidworks","mi","micro","micros","microsof","microsoft","microsoft visio","visio","oc","oo","p","q","structured query","r","salesforce","sec","ss","st","struct","us"]},{"id":185232,"userID":188492,"hired":0,"answer":"3-5 years of experience.","ed_level":"masters","name":"Instructional Designer","exp_level":"3-5","tags":["python","python programming","python programming language","ado","c","adobe","adobe photoshop","adobe indesign","design","os","x","java","programming languages","programming","java programming language","script","coding","structured query language","microsoft powerpoint","microsoft excel","ct","t","e","java prog","query","https","ja","javascript","mi","micro","micros","microsof","microsoft","p","q","structured query","r","st","struct"]}]},{"name":"Unknown","size":"3","children":[{"id":185232,"userID":171826,"hired":0,"answer":"","ed_level":"masters","name":"Instructional Designer","exp_level":"Unknown","tags":["microsoft access","enterprise miner","spss (math/stats pkg)","software","tableau software","software development","macromedia dreamweaver","ada","hypertext","c#","hypertext markup language","c# programming language","c programming language","oracle pl/sql programming language","c++ programming language","data mining","teradata (ncr data warehouseing product)","c","me","web technolog","web te","web","web technologies","os","mac","x","java","programming","pl/sql","oracle","ar","markup language","java programming language","sas enterprise miner","modeling experience","asic","script","php programming language","base","base sas","sas","visual basic","c++","structured query language","ca","cascading style sheets","sheets","microsoft excel","microsoft vis","tableau","data warehouse","css","ct","t","database","ibm db","e","ec","edi","ent","java prog","mining","ess","query","macromedia","microsoft visual c","sql","hp","ibm","ja","javascript","jmp","joomla","mi","micro","micros","microsof","microsoft","microsoft project","microsoft visual","microsoft visual c++","microstrategy","ml","ncr","oo","p","php","php programmin","pl/","q","structured query","r","rad","sp","sps","sq","ss","st","struct","teradata","us"]},{"id":185232,"userID":188447,"hired":0,"answer":"","ed_level":"masters","name":"Instructional Designer","exp_level":"Unknown","tags":["wealth management","risk ma","management","risk management","microsoft office","ado","c","me","adobe","financial","os","x","assessments","insurance","equity","financial industry","t","e","ent","ess","training","fixed income","ix","wealth manag","mi","micro","micros","microsof","microsoft","ncr","oc","q","r","ss","st","us"]},{"id":185232,"userID":188449,"hired":0,"answer":"","ed_level":"masters","name":"Instructional Designer","exp_level":"Unknown","tags":["user interface","link","customer relationship management","management","microsoft office","hypertext","hypertext markup language","data entry","ado","c","me","adobe","adobe illustrator","adobe photoshop","adobe premiere","design","ux design","interface design","web technolog","web te","web","web technologies","research","science","os","mac","x","support","applications","ar","markup language","english language","coding","ca","canvas","denebra canvas","cascading style sheets","sheets","cat","microsoft crm","microsoft powerpoint","css","t","e","ec","edi","ent","multimedia","macromedia flash","macromedia","gl","hub","internet","test","mi","micro","micros","microsof","microsoft","multi","p","r","relat","rf","ss","st","ul","us"]}]}]},{"name":"doctorate","size":1,"children":[{"name":"5+","size":"1","children":[{"id":185232,"userID":188504,"hired":0,"answer":"More than 5 years of experience.","ed_level":"doctorate","name":"Instructional Designer","exp_level":"5+","tags":["management","software","software engineering","hypertext","hypertext markup language","ado","c","me","adobe","computer aided software engineering","engineering","mac","x","human resources","ar","markup language","ca","cat","cisco","emc","security","video","t","publishing","ms","lotus notes","e","ec","edi","ent","multimedia","macromedia flash","macromedia","hr","sales","lms","lotus","multi","p","publications","r","sec","sourcing","ul","us"]}]},{"name":"1-2","size":"0","children":[""]},{"name":"3-5","size":"0","children":[""]},{"name":"Unknown","size":"0","children":[""]}]},{"name":"Unk/Other","size":4,"children":[{"name":"5+","size":"2","children":[{"id":185232,"userID":188469,"hired":0,"answer":"More than 5 years of experience.","ed_level":"Unk/Other","name":"Instructional Designer","exp_level":"5+","tags":["inventory control","project management","management","acquisitions","macromedia dreamweaver","active server pages","microsoft office","microsoft outlook","hypertext","hypertext markup language","ado","c","sharepoint","me","sharepoint technologies","adobe","adobe photoshop","adobe acrobat","design","interface design","financial","services","financial services","os","mac","x","support","applications","ar","markup language","script","scripting language","assessments","insurance","health insurance","inventory","financial industry","base","core based trees","real estate","inventor","ca","proc","cat","microsoft sharepoint","microsoft powerpoint","cmmi","macro (predefined code)","collection","collection procedures","complaints","security","ct","t","ms","outside sales","e","ec","economics","edi","emergency room","ent","multimedia","ess","training","macromedia flash","macromedia","git","icu","sales","test","technical writing","lms","medical","mi","micro","micros","microsof","microsoft","multi","nic","oc","oo","p","q","r","rf","scriptin","sec","sed","snagit","sp","ss","st","statistics","ul","us"]},{"id":185232,"userID":188493,"hired":0,"answer":"More than 5 years of experience.","ed_level":"Unk/Other","name":"Instructional Designer","exp_level":"5+","tags":["project management","management","customer service","ach","c","me","layout","human resources","support","technical support","english language","assessments","quality assurance","quality","bilingual","planning","capacity planning","ca","proc","coaching","security","ct","t","light emitting diode","e","ec","ent","ess","training","filing","gl","go","government","sales","test","mi","nic","oc","p","q","qual","r","recruiting","ria","roi","sec","ss","st","triage","us"]}]},{"name":"1-2","size":"1","children":[{"id":185232,"userID":188446,"hired":0,"answer":"1-2 years of experience.","ed_level":"Unk/Other","name":"Instructional Designer","exp_level":"1-2","tags":["macromedia dreamweaver","hypertext","hypertext markup language","ado","c","me","adobe","adobe photoshop","os","mac","x","ar","markup language","ca","cascading style sheets","sheets","microsoft powerpoint","information technology","technology","css","t","e","ec","edi","macromedia","mi","micro","micros","microsof","microsoft","orm","p","r","ss","st"]}]},{"name":"3-5","size":"0","children":[""]},{"name":"Unknown","size":"1","children":[{"id":185232,"userID":188467,"hired":0,"answer":"","ed_level":"Unk/Other","name":"Instructional Designer","exp_level":"Unknown","tags":["hypertext","french language","hypertext markup language","c","wordpress","os","x","ar","markup language","microsoft word","microsoft w","microsoft excel","t","e","ess","mi","micro","micros","microsof","microsoft","p","r","ss","surveys"]}]}]},{"name":"bachelors","size":10,"children":[{"name":"5+","size":"9","children":[{"id":185232,"userID":188463,"hired":0,"answer":"More than 5 years of experience.","ed_level":"bachelors","name":"Instructional Designer","exp_level":"5+","tags":["management","accounting","ado","c","me","adobe","mac","assessments","scheduling","ca","sheets","cat","personal conferencing specification (pcs)","t","e","ec","edi","ent","multimedia","ess","training","macromedia flash","macromedia","pc","jira","leadership","multi","oc","p","pcs","r","recruiting","retention","sp","ss","ul"]},{"id":185232,"userID":188511,"hired":0,"answer":"More than 5 years of experience.","ed_level":"bachelors","name":"Instructional Designer","exp_level":"5+","tags":["microsoft access","program management","management","ad hoc reports","microsoft office","microsoft outlook","c","sharepoint","me","sharepoint technologies","pricing","financial","financial analysis","os","x","architect","ar","architectural","base","business plan","forecast","medicare","ca","proc","microsoft powerpoint","microsoft excel","ct","t","database","e","ec","edi","ent","ess","federal tax","filing","hyperion","sales","mi","micro","micros","microsof","microsoft","oc","oo","p","procurement","r","salesforce","ss","st","us"]},{"id":185232,"userID":188459,"hired":0,"answer":"More than 5 years of experience.","ed_level":"bachelors","name":"Instructional Designer","exp_level":"5+","tags":["manager","program manager","project management","process management","customer relationship management","quality management","change management","microsoft change management","marketing management","management","asset management","software","bmc software","sql server","microsoft sql server","ado","c","sharepoint","me","sharepoint technologies","adobe","adobe photoshop","web services","services","web technolog","web te","object oriented analysis","web","web technologies","os","mac","x","human resources","ar","modeling experience","quality assurance","quality","audit","insurance","best practices","business modeling","business process modeling","documentum (wkflow sw)","sap fi module","sap","rational","firepond contact center","proc","consulting","microsoft w","supply chain","cobit","information technology","technology","object orien","ct","t","help desk","ms","documentum","dojo","lotus notes","e","ec","ecommerce","edi","ent","ess","training","macromedia","web ser","sql","ibm","sales training","sales","integrate","lms","lotus","mi","micro","micros","microsof","windows","microsoft","microsoft windows","microsoft windows nt","sql s","oc","oo","orm","p","procurement","q","qual","r","rationa","relat","remedy","siebel","sq","ss","st","ul","us","wi"]},{"id":185232,"userID":188476,"hired":0,"answer":"More than 5 years of experience.","ed_level":"bachelors","name":"Instructional Designer","exp_level":"5+","tags":["manager","time management","project management","management","project manager","microsoft outlook","hypertext","hypertext markup language","ado","c","me","adobe","adobe photoshop","advertising","design","financial","business analysis","business analyst","os","mac","x","java","benefits","design documents","oracle","ar","markup language","extensible markup language (xml)","script","assessments","quality assurance","quality","insurance","call center","financial industry","structured query language","ca","proc","consulting","microsoft internet explorer","microsoft powerpoint","microsoft vis","cms","video","construction","ct","t","ms","e","ec","edi","ent","multimedia","ess","query","macromedia flash","macromedia","lead generation","git","troubleshooting","process improvement","process improvements","internet","sales","its","ja","javascript","technical writing","lms","mi","micro","micros","microsof","microsoft","microsoft visio","visio","ml","multi","nic","oc","oo","p","q","qual","structured query","r","ria","schedule","sec","securities","siebel","snagit","ss","st","struct","triage","ul","us","xpl"]},{"id":185232,"userID":188444,"hired":0,"answer":"More than 5 years of experience.","ed_level":"bachelors","name":"Instructional Designer","exp_level":"5+","tags":["testing","regression testing","written communication skills","python","python programming","hyper text markup language","python programming language","communication skills","ado","c","me","adobe","agile","business development","os","x","framework","java","infrastructure","programming","ar","markup language","script","english language","quality assurance","quality","test plan","test plans","ca","cascading style sheets","sheets","test cases","cat","microsoft word","microsoft powerpoint","microsoft w","microsoft excel","communication","written communication","ct","t","e","ec","ent","ess","query","gl","ile","ja","javascript","jira","jquery","test","mba","mi","micro","micros","microsof","microsoft","nic","p","q","qual","r","ras","recruiting","samba","selenium","ss","st","struct","us"]},{"id":185232,"userID":188455,"hired":0,"answer":"More than 5 years of experience.","ed_level":"bachelors","name":"Instructional Designer","exp_level":"5+","tags":["project management","management","macromedia fireworks","ado","c","sharepoint","me","sharepoint technologies","adobe","adobe photoshop","adobe indesign","design","financial","web services","services","web technolog","web te","aml (macro lang)","web","web development","web technologies","science","os","mac","x","java","programming","support","technical support","oracle","ar","markup language","extensible markup language (xml)","java programming language","script","test script","assessments","rational","ca","consulting","security","ct","t","ms","e","ec","ecommerce","edi","ent","java prog","multimedia","ess","training","macromedia flash","macromedia","web ser","ibm","ibm websphere","integrate","intranet","ja","test","test scripts","lms","mi","ml","multi","nic","oc","p","r","rationa","sec","sp","ss","st","ul"]},{"id":185232,"userID":188456,"hired":0,"answer":"More than 5 years of experience.","ed_level":"bachelors","name":"Instructional Designer","exp_level":"5+","tags":["user documentation","microsoft access","content management","management","software","software development","microsoft windows x","windows x","python","hypertext","python programming","hypertext markup language","python programming language","ado","c","me","adobe","adobe photoshop","adobe framemaker","layout","wordpress","engineering","mechanical engineering","services","product development","business development","os","mac","apple mac os x","x","mac os x","apple","programming languages","programming","support","technical support","oracle","ar","markup language","php programming language","quality assurance","quality","coding","base","business objects","structured query language","confluence","ca","cascading style sheets","sheets","cat","public relations","microsoft word","microsoft powerpoint","microsoft w","microsoft excel","microsoft vis","citrix","cms","css","ct","final cut","t","database","relational database","mysql database","publishing","ms","e","ec","ent","ess","query","git","sql","hp","intranet","ix","jira","test","technical writing","mi","micro","micros","microsof","windows xp","windows","microsoft","microsoft visio","visio","microsoft windows","microsoft windows xp","mysql","nic","oc","p","php","php programmin","publications","q","qual","structured query","r","relat","snagit","sq","ss","st","struct","us","wi","xi","zendesk"]},{"id":185232,"userID":188475,"hired":0,"answer":"More than 5 years of experience.","ed_level":"bachelors","name":"Instructional Designer","exp_level":"5+","tags":["inventory control","c","advertising","os","x","inventory","retail","inventor","ca","cat","microsoft powerpoint","microsoft w","microsoft excel","communication","written communication","complaints","video","t","e","ent","mi","micro","micros","microsof","windows","microsoft","microsoft windows","monitoring","nic","p","r","referrals","wi"]},{"id":185232,"userID":188485,"hired":0,"answer":"More than 5 years of experience.","ed_level":"bachelors","name":"Instructional Designer","exp_level":"5+","tags":["manager","property management","project management","management","project manager","accounting","crystal reports","sql server","microsoft sql server","front office","c","sharepoint","me","sharepoint technologies","wordpress","services","professional services","os","ar","audit","ct","t","e","ec","ent","ess","sql","housekeeping","mi","micro","micros","microsof","microsoft","sql s","oc","p","q","r","sq","ss","st","us"]}]},{"name":"1-2","size":"1","children":[{"id":185232,"userID":188487,"hired":0,"answer":"1-2 years of experience.","ed_level":"bachelors","name":"Instructional Designer","exp_level":"1-2","tags":["hypertext","hypertext markup language","ado","c","me","adobe","adobe indesign","adobe framemaker","layout","design","wordpress","web technolog","web te","web","web technologies","os","x","ar","markup language","bash","ca","cascading style sheets","sheets","microsoft excel","video","css","final cut","t","e","ec","email","ent","ess","technical writing","mi","micro","micros","microsof","microsoft","nic","oc","p","r","ria","ss","st"]}]},{"name":"3-5","size":"0","children":[""]},{"name":"Unknown","size":"0","children":[""]}]},{"name":"associates","size":4,"children":[{"name":"5+","size":"3","children":[{"id":185232,"userID":188462,"hired":0,"answer":"More than 5 years of experience.","ed_level":"associates","name":"Instructional Designer","exp_level":"5+","tags":["time management","management","oral communications skills","c","me","science","relationship building","planning","ca","cat","communications","communication","t","e","ent","training","nic","p","r","relat"]},{"id":185232,"userID":188450,"hired":0,"answer":"More than 5 years of experience.","ed_level":"associates","name":"Instructional Designer","exp_level":"5+","tags":["project management","management","c","me","benefits","ar","proc","video","ct","t","e","ec","ent","training","icu","intranet","its","merchandising","oc","p","r","ul"]},{"id":185232,"userID":188457,"hired":0,"answer":"More than 5 years of experience.","ed_level":"associates","name":"Instructional Designer","exp_level":"5+","tags":["protocol","hypertext transfer protocol","accounting","software","macromedia dreamweaver","hypertext","ado","c","me","adobe","adobe illustrator","adobe photoshop","adobe acrobat","adobe indesign","design","graphic design","research","os","mac","x","ar","ca","proc","cat","catalogs","microsoft word","microsoft powerpoint","microsoft w","microsoft excel","market research","video","t","e","edi","ent","ess","macromedia flash","macromedia","process improvement","mi","micro","micros","microsof","microsoft","oc","p","packaging","r","ss","st","trans","us"]}]},{"name":"1-2","size":"0","children":[""]},{"name":"3-5","size":"0","children":[""]},{"name":"Unknown","size":"1","children":[{"id":185232,"userID":188494,"hired":0,"answer":"","ed_level":"associates","name":"Instructional Designer","exp_level":"Unknown","tags":["software","tableau software","sql server","microsoft sql server","c","os","x","applications","ar","asic","base","sas","visual basic","microsoft visual basic","ca","cat","microsoft w","microsoft excel","microsoft vis","cfa","tableau","t","database","postgres","mysql database","linux","unix","e","esql","sql","ix","matlab","mi","micro","micros","microsof","windows","microsoft","microsoft visual","microsoft visual ba","microsoft windows","sql s","mysql","nix","p","pos","postgresql","q","r","sq","st","wi"]}]}]},{"name":"cert/diploma","size":1,"children":[{"name":"5+","size":"1","children":[{"id":185232,"userID":188465,"hired":0,"answer":"More than 5 years of experience.","ed_level":"cert/diploma","name":"Instructional Designer","exp_level":"5+","tags":["analytical skills","written communication skills","communication skills","ado","c","adobe","adobe illustrator","adobe photoshop","adobe indesign","adobe premiere","design","research","os","x","ar","ca","cat","microsoft word","microsoft powerpoint","microsoft w","microsoft excel","microsoft vis","communication","written communication","video","t","e","training","mi","micro","micros","microsof","microsoft","microsoft visio","visio","nic","p","r","st","surgical","teller","us"]}]},{"name":"1-2","size":"0","children":[""]},{"name":"3-5","size":"0","children":[""]},{"name":"Unknown","size":"0","children":[""]}]}]}
